{"0":{"Rank":"274,543*","Names":"9th try","Link":"entry?entryID=36622363","R64":"250","R32":"280","R16":"200","R8":"80","R4":"0","R2":"0","Champ Pick":"Auburn","Total":"810","Percentile":"74.2"},"1":{"Rank":"274,543*","Names":"jcampbell1968 4","Link":"entry?entryID=20726924","R64":"270","R32":"260","R16":"200","R8":"80","R4":"0","R2":"0","Champ Pick":"Ohio State","Total":"810","Percentile":"74.2"},"2":{"Rank":"274,543*","Names":"jrg3200 1","Link":"entry?entryID=25930578","R64":"270","R32":"260","R16":"200","R8":"80","R4":"0","R2":"0","Champ Pick":"Duke","Total":"810","Percentile":"74.2"},"3":{"Rank":"274,543*","Names":"Kevin 2 ","Link":"entry?entryID=32259627","R64":"290","R32":"240","R16":"200","R8":"80","R4":"0","R2":"0","Champ Pick":"North Carolina","Total":"810","Percentile":"74.2"},"4":{"Rank":"274,543*","Names":"mitchell7216 5","Link":"entry?entryID=23281901","R64":"250","R32":"320","R16":"160","R8":"80","R4":"0","R2":"0","Champ Pick":"North Carolina","Total":"810","Percentile":"74.2"},"5":{"Rank":"274,543*","Names":"NTshortstop13 4","Link":"entry?entryID=34475544","R64":"250","R32":"320","R16":"160","R8":"80","R4":"0","R2":"0","Champ Pick":"North Carolina","Total":"810","Percentile":"74.2"},"6":{"Rank":"274,543*","Names":"Heifer PLEASE","Link":"entry?entryID=26977004","R64":"270","R32":"260","R16":"280","R8":"0","R4":"0","R2":"0","Champ Pick":"Gonzaga","Total":"810","Percentile":"74.2"},"7":{"Rank":"274,543*","Names":"danielhawkins24 1","Link":"entry?entryID=24685060","R64":"250","R32":"320","R16":"240","R8":"0","R4":"0","R2":"0","Champ Pick":"Duke","Total":"810","Percentile":"74.2"},"8":{"Rank":"274,543*","Names":"owen","Link":"entry?entryID=25898433","R64":"250","R32":"320","R16":"240","R8":"0","R4":"0","R2":"0","Champ Pick":"North Carolina","Total":"810","Percentile":"74.2"},"9":{"Rank":"274,543*","Names":"Ajdarr02 1","Link":"entry?entryID=22804995","R64":"150","R32":"60","R16":"40","R8":"80","R4":"160","R2":"320","Champ Pick":"Virginia","Total":"810","Percentile":"74.2"},"10":{"Rank":"274,543*","Names":"upset bracket 2","Link":"entry?entryID=26546188","R64":"190","R32":"220","R16":"160","R8":"80","R4":"160","R2":"0","Champ Pick":"Kentucky","Total":"810","Percentile":"74.2"},"11":{"Rank":"274,543*","Names":"22wilsonjr4 9","Link":"entry?entryID=31949944","R64":"190","R32":"220","R16":"160","R8":"80","R4":"160","R2":"0","Champ Pick":"VCU","Total":"810","Percentile":"74.2"},"12":{"Rank":"274,543*","Names":"bomberny50 3","Link":"entry?entryID=25774004","R64":"210","R32":"200","R16":"160","R8":"80","R4":"160","R2":"0","Champ Pick":"Duke","Total":"810","Percentile":"74.2"},"13":{"Rank":"274,543*","Names":"yaboy2","Link":"entry?entryID=23454798","R64":"230","R32":"180","R16":"160","R8":"80","R4":"160","R2":"0","Champ Pick":"Duke","Total":"810","Percentile":"74.2"},"14":{"Rank":"274,543*","Names":"Josh72658 2","Link":"entry?entryID=24728159","R64":"250","R32":"160","R16":"160","R8":"80","R4":"160","R2":"0","Champ Pick":"Duke","Total":"810","Percentile":"74.2"},"15":{"Rank":"274,543*","Names":"yaya227777 13","Link":"entry?entryID=25171796","R64":"230","R32":"220","R16":"120","R8":"80","R4":"160","R2":"0","Champ Pick":"Houston","Total":"810","Percentile":"74.2"},"16":{"Rank":"274,543*","Names":"cesh1","Link":"entry?entryID=25942052","R64":"230","R32":"220","R16":"120","R8":"80","R4":"160","R2":"0","Champ Pick":"Duke","Total":"810","Percentile":"74.2"},"17":{"Rank":"274,543*","Names":"MR.PERFECT2010 1","Link":"entry?entryID=27904041","R64":"230","R32":"220","R16":"120","R8":"80","R4":"160","R2":"0","Champ Pick":"Florida St","Total":"810","Percentile":"74.2"},"18":{"Rank":"274,543*","Names":"Mason Campbell 4","Link":"entry?entryID=25954323","R64":"250","R32":"200","R16":"120","R8":"80","R4":"160","R2":"0","Champ Pick":"Duke","Total":"810","Percentile":"74.2"},"19":{"Rank":"274,543*","Names":"espn03096333 5","Link":"entry?entryID=28141661","R64":"250","R32":"200","R16":"120","R8":"80","R4":"160","R2":"0","Champ Pick":"Duke","Total":"810","Percentile":"74.2"},"20":{"Rank":"274,543*","Names":"jlue Zags","Link":"entry?entryID=26474416","R64":"250","R32":"240","R16":"80","R8":"80","R4":"160","R2":"0","Champ Pick":"Gonzaga","Total":"810","Percentile":"74.2"},"21":{"Rank":"274,543*","Names":"willierounaghi 3","Link":"entry?entryID=24228508","R64":"210","R32":"200","R16":"160","R8":"240","R4":"0","R2":"0","Champ Pick":"Michigan State","Total":"810","Percentile":"74.2"},"22":{"Rank":"274,543*","Names":"noahbad1 3","Link":"entry?entryID=27561940","R64":"210","R32":"240","R16":"200","R8":"160","R4":"0","R2":"0","Champ Pick":"Michigan State","Total":"810","Percentile":"74.2"},"23":{"Rank":"274,543*","Names":"Zaddy3","Link":"entry?entryID=31352589","R64":"210","R32":"240","R16":"200","R8":"160","R4":"0","R2":"0","Champ Pick":"Michigan State","Total":"810","Percentile":"74.2"},"24":{"Rank":"274,543*","Names":"Logan Baylor 3","Link":"entry?entryID=22107238","R64":"250","R32":"200","R16":"200","R8":"160","R4":"0","R2":"0","Champ Pick":"North Carolina","Total":"810","Percentile":"74.2"},"25":{"Rank":"274,543*","Names":"espn58082768 3","Link":"entry?entryID=25846730","R64":"250","R32":"200","R16":"200","R8":"160","R4":"0","R2":"0","Champ Pick":"Michigan State","Total":"810","Percentile":"74.2"},"26":{"Rank":"274,543*","Names":"Zags 1","Link":"entry?entryID=30157742","R64":"250","R32":"200","R16":"200","R8":"160","R4":"0","R2":"0","Champ Pick":"Gonzaga","Total":"810","Percentile":"74.2"},"27":{"Rank":"274,543*","Names":"Worst Team in the League","Link":"entry?entryID=18656015","R64":"230","R32":"260","R16":"160","R8":"160","R4":"0","R2":"0","Champ Pick":"North Carolina","Total":"810","Percentile":"74.2"},"28":{"Rank":"274,543*","Names":"espn61781482 13","Link":"entry?entryID=28402280","R64":"230","R32":"260","R16":"160","R8":"160","R4":"0","R2":"0","Champ Pick":"Michigan","Total":"810","Percentile":"74.2"},"29":{"Rank":"274,543*","Names":"fun","Link":"entry?entryID=28889211","R64":"230","R32":"260","R16":"160","R8":"160","R4":"0","R2":"0","Champ Pick":"Kentucky","Total":"810","Percentile":"74.2"},"30":{"Rank":"274,543*","Names":"1st","Link":"entry?entryID=21907809","R64":"250","R32":"240","R16":"160","R8":"160","R4":"0","R2":"0","Champ Pick":"Duke","Total":"810","Percentile":"74.2"},"31":{"Rank":"274,543*","Names":"Tank4Tua","Link":"entry?entryID=22089229","R64":"250","R32":"240","R16":"160","R8":"160","R4":"0","R2":"0","Champ Pick":"North Carolina","Total":"810","Percentile":"74.2"},"32":{"Rank":"274,543*","Names":"ken3","Link":"entry?entryID=24402747","R64":"250","R32":"240","R16":"160","R8":"160","R4":"0","R2":"0","Champ Pick":"North Carolina","Total":"810","Percentile":"74.2"},"33":{"Rank":"274,543*","Names":"Andres #4","Link":"entry?entryID=25823924","R64":"250","R32":"240","R16":"160","R8":"160","R4":"0","R2":"0","Champ Pick":"Michigan State","Total":"810","Percentile":"74.2"},"34":{"Rank":"274,543*","Names":"BigDaddyN8 4","Link":"entry?entryID=29473260","R64":"250","R32":"240","R16":"160","R8":"160","R4":"0","R2":"0","Champ Pick":"Michigan State","Total":"810","Percentile":"74.2"},"35":{"Rank":"274,543*","Names":"espnfan3051526223 1","Link":"entry?entryID=22998046","R64":"210","R32":"280","R16":"240","R8":"80","R4":"0","R2":"0","Champ Pick":"Duke","Total":"810","Percentile":"74.2"},"36":{"Rank":"274,543*","Names":"vjkjsdafhkas","Link":"entry?entryID=25456610","R64":"210","R32":"280","R16":"240","R8":"80","R4":"0","R2":"0","Champ Pick":"North Carolina","Total":"810","Percentile":"74.2"},"37":{"Rank":"274,543*","Names":"jjohnson1986 1","Link":"entry?entryID=22131964","R64":"230","R32":"260","R16":"240","R8":"80","R4":"0","R2":"0","Champ Pick":"Duke","Total":"810","Percentile":"74.2"},"38":{"Rank":"274,543*","Names":"Reddish2","Link":"entry?entryID=26233407","R64":"230","R32":"260","R16":"240","R8":"80","R4":"0","R2":"0","Champ Pick":"Duke","Total":"810","Percentile":"74.2"},"39":{"Rank":"274,543*","Names":"lukemitch24 2","Link":"entry?entryID=28906418","R64":"230","R32":"260","R16":"240","R8":"80","R4":"0","R2":"0","Champ Pick":"Duke","Total":"810","Percentile":"74.2"},"40":{"Rank":"274,543*","Names":"espnfan0272876755 2","Link":"entry?entryID=31324277","R64":"230","R32":"260","R16":"240","R8":"80","R4":"0","R2":"0","Champ Pick":"Michigan State","Total":"810","Percentile":"74.2"},"41":{"Rank":"274,543*","Names":"MckayBreshears 1","Link":"entry?entryID=18979417","R64":"250","R32":"240","R16":"240","R8":"80","R4":"0","R2":"0","Champ Pick":"Duke","Total":"810","Percentile":"74.2"},"42":{"Rank":"274,543*","Names":"Owen Christopher ","Link":"entry?entryID=18986565","R64":"250","R32":"240","R16":"240","R8":"80","R4":"0","R2":"0","Champ Pick":"Duke","Total":"810","Percentile":"74.2"},"43":{"Rank":"274,543*","Names":"espn38364513 2","Link":"entry?entryID=26945367","R64":"250","R32":"240","R16":"240","R8":"80","R4":"0","R2":"0","Champ Pick":"Duke","Total":"810","Percentile":"74.2"},"44":{"Rank":"274,543*","Names":"The Winner","Link":"entry?entryID=31443064","R64":"250","R32":"240","R16":"240","R8":"80","R4":"0","R2":"0","Champ Pick":"Michigan","Total":"810","Percentile":"74.2"},"45":{"Rank":"274,543*","Names":"Michiganfan8605 2","Link":"entry?entryID=33213141","R64":"250","R32":"240","R16":"240","R8":"80","R4":"0","R2":"0","Champ Pick":"Duke","Total":"810","Percentile":"74.2"},"46":{"Rank":"274,543*","Names":"BT EXPRESS 31 2","Link":"entry?entryID=27364338","R64":"210","R32":"320","R16":"200","R8":"80","R4":"0","R2":"0","Champ Pick":"Gonzaga","Total":"810","Percentile":"74.2"},"47":{"Rank":"274,543*","Names":"filoBALLLLLIN","Link":"entry?entryID=18594152","R64":"230","R32":"300","R16":"200","R8":"80","R4":"0","R2":"0","Champ Pick":"Duke","Total":"810","Percentile":"74.2"},"48":{"Rank":"274,543*","Names":"Flavor Saver","Link":"entry?entryID=18986194","R64":"230","R32":"300","R16":"200","R8":"80","R4":"0","R2":"0","Champ Pick":"Duke","Total":"810","Percentile":"74.2"},"49":{"Rank":"274,543*","Names":"Purdue Mch St","Link":"entry?entryID=23173221","R64":"230","R32":"300","R16":"200","R8":"80","R4":"0","R2":"0","Champ Pick":"Purdue","Total":"810","Percentile":"74.2"}}