{"0":{"Rank":"383,278*","Names":"PittsburghSteelers0215 1","Link":"entry?entryID=18634345","R64":"230","R32":"240","R16":"200","R8":"80","R4":"0","R2":"0","Champ Pick":"Duke","Total":"750","Percentile":"63.4"},"1":{"Rank":"383,278*","Names":"Daless8194646 1","Link":"entry?entryID=18649706","R64":"230","R32":"240","R16":"200","R8":"80","R4":"0","R2":"0","Champ Pick":"North Carolina","Total":"750","Percentile":"63.4"},"2":{"Rank":"383,278*","Names":"Kevin M.","Link":"entry?entryID=18651482","R64":"230","R32":"240","R16":"200","R8":"80","R4":"0","R2":"0","Champ Pick":"Duke","Total":"750","Percentile":"63.4"},"3":{"Rank":"383,278*","Names":"austin8599608 5","Link":"entry?entryID=18667935","R64":"230","R32":"240","R16":"200","R8":"80","R4":"0","R2":"0","Champ Pick":"Duke","Total":"750","Percentile":"63.4"},"4":{"Rank":"383,278*","Names":"Smac_07 1","Link":"entry?entryID=18730646","R64":"230","R32":"240","R16":"200","R8":"80","R4":"0","R2":"0","Champ Pick":"North Carolina","Total":"750","Percentile":"63.4"},"5":{"Rank":"383,278*","Names":"Albert4252 1","Link":"entry?entryID=18824978","R64":"230","R32":"240","R16":"200","R8":"80","R4":"0","R2":"0","Champ Pick":"Duke","Total":"750","Percentile":"63.4"},"6":{"Rank":"383,278*","Names":"Taraaa1126 1","Link":"entry?entryID=18845736","R64":"230","R32":"240","R16":"200","R8":"80","R4":"0","R2":"0","Champ Pick":"Gonzaga","Total":"750","Percentile":"63.4"},"7":{"Rank":"383,278*","Names":"Gage1","Link":"entry?entryID=18943036","R64":"230","R32":"240","R16":"200","R8":"80","R4":"0","R2":"0","Champ Pick":"Michigan","Total":"750","Percentile":"63.4"},"8":{"Rank":"383,278*","Names":"edmond8109450 1","Link":"entry?entryID=19003825","R64":"230","R32":"240","R16":"200","R8":"80","R4":"0","R2":"0","Champ Pick":"Duke","Total":"750","Percentile":"63.4"},"9":{"Rank":"383,278*","Names":"biggggsean 2","Link":"entry?entryID=19018206","R64":"230","R32":"240","R16":"200","R8":"80","R4":"0","R2":"0","Champ Pick":"North Carolina","Total":"750","Percentile":"63.4"},"10":{"Rank":"383,278*","Names":"fflitt","Link":"entry?entryID=19074397","R64":"230","R32":"240","R16":"200","R8":"80","R4":"0","R2":"0","Champ Pick":"Duke","Total":"750","Percentile":"63.4"},"11":{"Rank":"383,278*","Names":"mosey","Link":"entry?entryID=19121864","R64":"230","R32":"240","R16":"200","R8":"80","R4":"0","R2":"0","Champ Pick":"North Carolina","Total":"750","Percentile":"63.4"},"12":{"Rank":"383,278*","Names":"Stach","Link":"entry?entryID=19229474","R64":"230","R32":"240","R16":"200","R8":"80","R4":"0","R2":"0","Champ Pick":"Kentucky","Total":"750","Percentile":"63.4"},"13":{"Rank":"383,278*","Names":"berto84bori 1","Link":"entry?entryID=19429180","R64":"230","R32":"240","R16":"200","R8":"80","R4":"0","R2":"0","Champ Pick":"North Carolina","Total":"750","Percentile":"63.4"},"14":{"Rank":"383,278*","Names":"Doughboy\ud83d\ude42","Link":"entry?entryID=19440672","R64":"230","R32":"240","R16":"200","R8":"80","R4":"0","R2":"0","Champ Pick":"North Carolina","Total":"750","Percentile":"63.4"},"15":{"Rank":"383,278*","Names":"vrs07","Link":"entry?entryID=19554490","R64":"230","R32":"240","R16":"200","R8":"80","R4":"0","R2":"0","Champ Pick":"North Carolina","Total":"750","Percentile":"63.4"},"16":{"Rank":"383,278*","Names":"katie706 1","Link":"entry?entryID=19617147","R64":"230","R32":"240","R16":"200","R8":"80","R4":"0","R2":"0","Champ Pick":"Duke","Total":"750","Percentile":"63.4"},"17":{"Rank":"383,278*","Names":"Goose9178868 1","Link":"entry?entryID=19628116","R64":"230","R32":"240","R16":"200","R8":"80","R4":"0","R2":"0","Champ Pick":"Duke","Total":"750","Percentile":"63.4"},"18":{"Rank":"383,278*","Names":"Young2","Link":"entry?entryID=19807830","R64":"230","R32":"240","R16":"200","R8":"80","R4":"0","R2":"0","Champ Pick":"Duke","Total":"750","Percentile":"63.4"},"19":{"Rank":"383,278*","Names":"Chaseransdell 1","Link":"entry?entryID=19979341","R64":"230","R32":"240","R16":"200","R8":"80","R4":"0","R2":"0","Champ Pick":"Duke","Total":"750","Percentile":"63.4"},"20":{"Rank":"383,278*","Names":"Brandon\u2019s bracket","Link":"entry?entryID=20006721","R64":"230","R32":"240","R16":"200","R8":"80","R4":"0","R2":"0","Champ Pick":"Duke","Total":"750","Percentile":"63.4"},"21":{"Rank":"383,278*","Names":"DUKE","Link":"entry?entryID=20010468","R64":"230","R32":"240","R16":"200","R8":"80","R4":"0","R2":"0","Champ Pick":"Duke","Total":"750","Percentile":"63.4"},"22":{"Rank":"383,278*","Names":"Alex0773 1","Link":"entry?entryID=20031684","R64":"230","R32":"240","R16":"200","R8":"80","R4":"0","R2":"0","Champ Pick":"Michigan","Total":"750","Percentile":"63.4"},"23":{"Rank":"383,278*","Names":"6842eric 1","Link":"entry?entryID=20144051","R64":"230","R32":"240","R16":"200","R8":"80","R4":"0","R2":"0","Champ Pick":"Duke","Total":"750","Percentile":"63.4"},"24":{"Rank":"383,278*","Names":"dannyd8330955 3","Link":"entry?entryID=20377730","R64":"230","R32":"240","R16":"200","R8":"80","R4":"0","R2":"0","Champ Pick":"Duke","Total":"750","Percentile":"63.4"},"25":{"Rank":"383,278*","Names":"espn01004216 1","Link":"entry?entryID=20470598","R64":"230","R32":"240","R16":"200","R8":"80","R4":"0","R2":"0","Champ Pick":"Gonzaga","Total":"750","Percentile":"63.4"},"26":{"Rank":"383,278*","Names":"2002osubuck 2","Link":"entry?entryID=20573282","R64":"230","R32":"240","R16":"200","R8":"80","R4":"0","R2":"0","Champ Pick":"Michigan","Total":"750","Percentile":"63.4"},"27":{"Rank":"383,278*","Names":"_BeardedWonder_ 5","Link":"entry?entryID=20733047","R64":"230","R32":"240","R16":"200","R8":"80","R4":"0","R2":"0","Champ Pick":"North Carolina","Total":"750","Percentile":"63.4"},"28":{"Rank":"383,278*","Names":"Whiney Winners1","Link":"entry?entryID=20778516","R64":"230","R32":"240","R16":"200","R8":"80","R4":"0","R2":"0","Champ Pick":"North Carolina","Total":"750","Percentile":"63.4"},"29":{"Rank":"383,278*","Names":"t hall2 2","Link":"entry?entryID=20828274","R64":"230","R32":"240","R16":"200","R8":"80","R4":"0","R2":"0","Champ Pick":"Kentucky","Total":"750","Percentile":"63.4"},"30":{"Rank":"383,278*","Names":"P Loaf 1","Link":"entry?entryID=20836359","R64":"230","R32":"240","R16":"200","R8":"80","R4":"0","R2":"0","Champ Pick":"Duke","Total":"750","Percentile":"63.4"},"31":{"Rank":"383,278*","Names":"gimme7s 3","Link":"entry?entryID=20930483","R64":"230","R32":"240","R16":"200","R8":"80","R4":"0","R2":"0","Champ Pick":"Duke","Total":"750","Percentile":"63.4"},"32":{"Rank":"383,278*","Names":"ryanflem","Link":"entry?entryID=20974415","R64":"230","R32":"240","R16":"200","R8":"80","R4":"0","R2":"0","Champ Pick":"Duke","Total":"750","Percentile":"63.4"},"33":{"Rank":"383,278*","Names":"LouCleve 9","Link":"entry?entryID=21067444","R64":"230","R32":"240","R16":"200","R8":"80","R4":"0","R2":"0","Champ Pick":"Duke","Total":"750","Percentile":"63.4"},"34":{"Rank":"383,278*","Names":"kariha1800262 6","Link":"entry?entryID=21170260","R64":"230","R32":"240","R16":"200","R8":"80","R4":"0","R2":"0","Champ Pick":"Duke","Total":"750","Percentile":"63.4"},"35":{"Rank":"383,278*","Names":"TEEJ","Link":"entry?entryID=21370361","R64":"230","R32":"240","R16":"200","R8":"80","R4":"0","R2":"0","Champ Pick":"Tennessee","Total":"750","Percentile":"63.4"},"36":{"Rank":"383,278*","Names":"tylerz108","Link":"entry?entryID=21411763","R64":"230","R32":"240","R16":"200","R8":"80","R4":"0","R2":"0","Champ Pick":"North Carolina","Total":"750","Percentile":"63.4"},"37":{"Rank":"383,278*","Names":"sol jacobs 1","Link":"entry?entryID=21499627","R64":"230","R32":"240","R16":"200","R8":"80","R4":"0","R2":"0","Champ Pick":"Tennessee","Total":"750","Percentile":"63.4"},"38":{"Rank":"383,278*","Names":"ajhessel 1","Link":"entry?entryID=21569797","R64":"230","R32":"240","R16":"200","R8":"80","R4":"0","R2":"0","Champ Pick":"Duke","Total":"750","Percentile":"63.4"},"39":{"Rank":"383,278*","Names":"countrybooy","Link":"entry?entryID=21583126","R64":"230","R32":"240","R16":"200","R8":"80","R4":"0","R2":"0","Champ Pick":"Gonzaga","Total":"750","Percentile":"63.4"},"40":{"Rank":"383,278*","Names":"George7917 1","Link":"entry?entryID=21710591","R64":"230","R32":"240","R16":"200","R8":"80","R4":"0","R2":"0","Champ Pick":"North Carolina","Total":"750","Percentile":"63.4"},"41":{"Rank":"383,278*","Names":"decker549 1","Link":"entry?entryID=21711791","R64":"230","R32":"240","R16":"200","R8":"80","R4":"0","R2":"0","Champ Pick":"North Carolina","Total":"750","Percentile":"63.4"},"42":{"Rank":"383,278*","Names":"lil boosie903 2","Link":"entry?entryID=21716932","R64":"230","R32":"240","R16":"200","R8":"80","R4":"0","R2":"0","Champ Pick":"Kentucky","Total":"750","Percentile":"63.4"},"43":{"Rank":"383,278*","Names":"Cody37810 4","Link":"entry?entryID=21829459","R64":"230","R32":"240","R16":"200","R8":"80","R4":"0","R2":"0","Champ Pick":"Duke","Total":"750","Percentile":"63.4"},"44":{"Rank":"383,278*","Names":"Random 2","Link":"entry?entryID=21844094","R64":"230","R32":"240","R16":"200","R8":"80","R4":"0","R2":"0","Champ Pick":"Duke","Total":"750","Percentile":"63.4"},"45":{"Rank":"383,278*","Names":"Matthew Coklan 2","Link":"entry?entryID=22300791","R64":"230","R32":"240","R16":"200","R8":"80","R4":"0","R2":"0","Champ Pick":"Duke","Total":"750","Percentile":"63.4"},"46":{"Rank":"383,278*","Names":"elisha8451990 5","Link":"entry?entryID=22397037","R64":"230","R32":"240","R16":"200","R8":"80","R4":"0","R2":"0","Champ Pick":"Duke","Total":"750","Percentile":"63.4"},"47":{"Rank":"383,278*","Names":"friz4 1","Link":"entry?entryID=22429454","R64":"230","R32":"240","R16":"200","R8":"80","R4":"0","R2":"0","Champ Pick":"Duke","Total":"750","Percentile":"63.4"},"48":{"Rank":"383,278*","Names":"espnfan7698952994 1","Link":"entry?entryID=22642060","R64":"230","R32":"240","R16":"200","R8":"80","R4":"0","R2":"0","Champ Pick":"Duke","Total":"750","Percentile":"63.4"},"49":{"Rank":"383,278*","Names":"SirCassi 5","Link":"entry?entryID=22823805","R64":"230","R32":"240","R16":"200","R8":"80","R4":"0","R2":"0","Champ Pick":"North Carolina","Total":"750","Percentile":"63.4"}}