{"0":{"Rank":"901,175*","Names":"Elciccione 1","Link":"entry?entryID=21613615","R64":"210","R32":"180","R16":"120","R8":"0","R4":"0","R2":"0","Champ Pick":"Duke","Total":"510","Percentile":"11.0"},"1":{"Rank":"901,175*","Names":"espn48324473 20","Link":"entry?entryID=21626232","R64":"210","R32":"180","R16":"120","R8":"0","R4":"0","R2":"0","Champ Pick":"Duke","Total":"510","Percentile":"11.0"},"2":{"Rank":"901,175*","Names":"Pujols082172 6","Link":"entry?entryID=21893599","R64":"210","R32":"180","R16":"120","R8":"0","R4":"0","R2":"0","Champ Pick":"Tennessee","Total":"510","Percentile":"11.0"},"3":{"Rank":"901,175*","Names":"ismellcinarolls 2","Link":"entry?entryID=22171046","R64":"210","R32":"180","R16":"120","R8":"0","R4":"0","R2":"0","Champ Pick":"Duke","Total":"510","Percentile":"11.0"},"4":{"Rank":"901,175*","Names":"tywizzler 1","Link":"entry?entryID=23080920","R64":"210","R32":"180","R16":"120","R8":"0","R4":"0","R2":"0","Champ Pick":"Duke","Total":"510","Percentile":"11.0"},"5":{"Rank":"901,175*","Names":"Harris9090968 6","Link":"entry?entryID=25485942","R64":"210","R32":"180","R16":"120","R8":"0","R4":"0","R2":"0","Champ Pick":"Duke","Total":"510","Percentile":"11.0"},"6":{"Rank":"901,175*","Names":"RDGoober01 7","Link":"entry?entryID=25699381","R64":"210","R32":"180","R16":"120","R8":"0","R4":"0","R2":"0","Champ Pick":"North Carolina","Total":"510","Percentile":"11.0"},"7":{"Rank":"901,175*","Names":"Sam 9","Link":"entry?entryID=25748032","R64":"210","R32":"180","R16":"120","R8":"0","R4":"0","R2":"0","Champ Pick":"Duke","Total":"510","Percentile":"11.0"},"8":{"Rank":"901,175*","Names":"jcb4clemson 10","Link":"entry?entryID=26723651","R64":"210","R32":"180","R16":"120","R8":"0","R4":"0","R2":"0","Champ Pick":"Marquette","Total":"510","Percentile":"11.0"},"9":{"Rank":"901,175*","Names":"flip of the coin","Link":"entry?entryID=27492460","R64":"210","R32":"180","R16":"120","R8":"0","R4":"0","R2":"0","Champ Pick":"Duke","Total":"510","Percentile":"11.0"},"10":{"Rank":"901,175*","Names":"Terence375 1","Link":"entry?entryID=28013020","R64":"210","R32":"180","R16":"120","R8":"0","R4":"0","R2":"0","Champ Pick":"Duke","Total":"510","Percentile":"11.0"},"11":{"Rank":"901,175*","Names":"espn00473113 1","Link":"entry?entryID=28699514","R64":"210","R32":"180","R16":"120","R8":"0","R4":"0","R2":"0","Champ Pick":"North Carolina","Total":"510","Percentile":"11.0"},"12":{"Rank":"901,175*","Names":"cpalioto42 2","Link":"entry?entryID=29301708","R64":"210","R32":"180","R16":"120","R8":"0","R4":"0","R2":"0","Champ Pick":"Duke","Total":"510","Percentile":"11.0"},"13":{"Rank":"901,175*","Names":"Levi Crowl 47","Link":"entry?entryID=29449577","R64":"210","R32":"180","R16":"120","R8":"0","R4":"0","R2":"0","Champ Pick":"North Carolina","Total":"510","Percentile":"11.0"},"14":{"Rank":"901,175*","Names":"Nate.Ski 3","Link":"entry?entryID=30940490","R64":"210","R32":"180","R16":"120","R8":"0","R4":"0","R2":"0","Champ Pick":"Michigan","Total":"510","Percentile":"11.0"},"15":{"Rank":"901,175*","Names":"mat 16","Link":"entry?entryID=31146571","R64":"210","R32":"180","R16":"120","R8":"0","R4":"0","R2":"0","Champ Pick":"Duke","Total":"510","Percentile":"11.0"},"16":{"Rank":"901,175*","Names":"SnookeyNeka 1","Link":"entry?entryID=31232110","R64":"210","R32":"180","R16":"120","R8":"0","R4":"0","R2":"0","Champ Pick":"North Carolina","Total":"510","Percentile":"11.0"},"17":{"Rank":"901,175*","Names":"KCFraz","Link":"entry?entryID=32323411","R64":"210","R32":"180","R16":"120","R8":"0","R4":"0","R2":"0","Champ Pick":"Michigan","Total":"510","Percentile":"11.0"},"18":{"Rank":"901,175*","Names":"ohioplayerss 5","Link":"entry?entryID=32950674","R64":"210","R32":"180","R16":"120","R8":"0","R4":"0","R2":"0","Champ Pick":"Duke","Total":"510","Percentile":"11.0"},"19":{"Rank":"901,175*","Names":"yeehAAh","Link":"entry?entryID=34370228","R64":"210","R32":"180","R16":"120","R8":"0","R4":"0","R2":"0","Champ Pick":"Tennessee","Total":"510","Percentile":"11.0"},"20":{"Rank":"901,175*","Names":"brecke2388759 9","Link":"entry?entryID=34415768","R64":"210","R32":"180","R16":"120","R8":"0","R4":"0","R2":"0","Champ Pick":"Murray State","Total":"510","Percentile":"11.0"},"21":{"Rank":"901,175*","Names":"big baller ft brodie 9","Link":"entry?entryID=34757370","R64":"210","R32":"180","R16":"120","R8":"0","R4":"0","R2":"0","Champ Pick":"North Carolina","Total":"510","Percentile":"11.0"},"22":{"Rank":"901,175*","Names":"Jolody 25","Link":"entry?entryID=36558923","R64":"210","R32":"180","R16":"120","R8":"0","R4":"0","R2":"0","Champ Pick":"Duke","Total":"510","Percentile":"11.0"},"23":{"Rank":"901,175*","Names":"josh_Number07 24","Link":"entry?entryID=36820454","R64":"210","R32":"180","R16":"120","R8":"0","R4":"0","R2":"0","Champ Pick":"Duke","Total":"510","Percentile":"11.0"},"24":{"Rank":"901,175*","Names":"Trevort296 1","Link":"entry?entryID=20230445","R64":"230","R32":"160","R16":"120","R8":"0","R4":"0","R2":"0","Champ Pick":"Duke","Total":"510","Percentile":"11.0"},"25":{"Rank":"901,175*","Names":"Real","Link":"entry?entryID=20410166","R64":"230","R32":"160","R16":"120","R8":"0","R4":"0","R2":"0","Champ Pick":"Tennessee","Total":"510","Percentile":"11.0"},"26":{"Rank":"901,175*","Names":"SamBudin 1","Link":"entry?entryID=22289067","R64":"230","R32":"160","R16":"120","R8":"0","R4":"0","R2":"0","Champ Pick":"Duke","Total":"510","Percentile":"11.0"},"27":{"Rank":"901,175*","Names":"Caleb_denham23 4","Link":"entry?entryID=23167080","R64":"230","R32":"160","R16":"120","R8":"0","R4":"0","R2":"0","Champ Pick":"Duke","Total":"510","Percentile":"11.0"},"28":{"Rank":"901,175*","Names":"espn57960233 2","Link":"entry?entryID=23247532","R64":"230","R32":"160","R16":"120","R8":"0","R4":"0","R2":"0","Champ Pick":"Michigan","Total":"510","Percentile":"11.0"},"29":{"Rank":"901,175*","Names":"Upsets all day","Link":"entry?entryID=23304760","R64":"230","R32":"160","R16":"120","R8":"0","R4":"0","R2":"0","Champ Pick":"Duke","Total":"510","Percentile":"11.0"},"30":{"Rank":"901,175*","Names":"maxgaudreauruel","Link":"entry?entryID=23604399","R64":"230","R32":"160","R16":"120","R8":"0","R4":"0","R2":"0","Champ Pick":"Duke","Total":"510","Percentile":"11.0"},"31":{"Rank":"901,175*","Names":"HYShoes 5","Link":"entry?entryID=24191491","R64":"230","R32":"160","R16":"120","R8":"0","R4":"0","R2":"0","Champ Pick":"Gonzaga","Total":"510","Percentile":"11.0"},"32":{"Rank":"901,175*","Names":"reload","Link":"entry?entryID=25548283","R64":"230","R32":"160","R16":"120","R8":"0","R4":"0","R2":"0","Champ Pick":"Gonzaga","Total":"510","Percentile":"11.0"},"33":{"Rank":"901,175*","Names":"Trash1","Link":"entry?entryID=26788354","R64":"230","R32":"160","R16":"120","R8":"0","R4":"0","R2":"0","Champ Pick":"Duke","Total":"510","Percentile":"11.0"},"34":{"Rank":"901,175*","Names":"OneTeamOneDream","Link":"entry?entryID=28895775","R64":"230","R32":"160","R16":"120","R8":"0","R4":"0","R2":"0","Champ Pick":"Duke","Total":"510","Percentile":"11.0"},"35":{"Rank":"901,175*","Names":"benkoeck 3","Link":"entry?entryID=29211728","R64":"230","R32":"160","R16":"120","R8":"0","R4":"0","R2":"0","Champ Pick":"North Carolina","Total":"510","Percentile":"11.0"},"36":{"Rank":"901,175*","Names":"espn35866491 1","Link":"entry?entryID=29441377","R64":"230","R32":"160","R16":"120","R8":"0","R4":"0","R2":"0","Champ Pick":"Duke","Total":"510","Percentile":"11.0"},"37":{"Rank":"901,175*","Names":"starkj9259395 4","Link":"entry?entryID=30144757","R64":"230","R32":"160","R16":"120","R8":"0","R4":"0","R2":"0","Champ Pick":"Tennessee","Total":"510","Percentile":"11.0"},"38":{"Rank":"901,175*","Names":"BUDLIGHTKID25 2","Link":"entry?entryID=32723562","R64":"230","R32":"160","R16":"120","R8":"0","R4":"0","R2":"0","Champ Pick":"Tennessee","Total":"510","Percentile":"11.0"},"39":{"Rank":"901,175*","Names":"espn12338626 24","Link":"entry?entryID=32894060","R64":"230","R32":"160","R16":"120","R8":"0","R4":"0","R2":"0","Champ Pick":"Duke","Total":"510","Percentile":"11.0"},"40":{"Rank":"901,175*","Names":"Seth7603 5","Link":"entry?entryID=34746151","R64":"230","R32":"160","R16":"120","R8":"0","R4":"0","R2":"0","Champ Pick":"North Carolina","Total":"510","Percentile":"11.0"},"41":{"Rank":"901,175*","Names":"frostyboi1217 1","Link":"entry?entryID=35476785","R64":"230","R32":"160","R16":"120","R8":"0","R4":"0","R2":"0","Champ Pick":"North Carolina","Total":"510","Percentile":"11.0"},"42":{"Rank":"901,175*","Names":"Peytonwhited5","Link":"entry?entryID=36263788","R64":"230","R32":"160","R16":"120","R8":"0","R4":"0","R2":"0","Champ Pick":"Duke","Total":"510","Percentile":"11.0"},"43":{"Rank":"901,175*","Names":"Sarah.dewolfe 1","Link":"entry?entryID=20861128","R64":"250","R32":"140","R16":"120","R8":"0","R4":"0","R2":"0","Champ Pick":"Gonzaga","Total":"510","Percentile":"11.0"},"44":{"Rank":"901,175*","Names":"tmkoop7342648 2","Link":"entry?entryID=21367038","R64":"250","R32":"140","R16":"120","R8":"0","R4":"0","R2":"0","Champ Pick":"Duke","Total":"510","Percentile":"11.0"},"45":{"Rank":"901,175*","Names":"Piano","Link":"entry?entryID=23455918","R64":"250","R32":"140","R16":"120","R8":"0","R4":"0","R2":"0","Champ Pick":"Duke","Total":"510","Percentile":"11.0"},"46":{"Rank":"901,175*","Names":"tfrien3199241 8","Link":"entry?entryID=25766826","R64":"170","R32":"260","R16":"80","R8":"0","R4":"0","R2":"0","Champ Pick":"Florida St","Total":"510","Percentile":"11.0"},"47":{"Rank":"901,175*","Names":"distefano1234 4","Link":"entry?entryID=33019858","R64":"190","R32":"240","R16":"80","R8":"0","R4":"0","R2":"0","Champ Pick":"North Carolina","Total":"510","Percentile":"11.0"},"48":{"Rank":"901,175*","Names":"Jordaja 1","Link":"entry?entryID=19176482","R64":"210","R32":"220","R16":"80","R8":"0","R4":"0","R2":"0","Champ Pick":"North Carolina","Total":"510","Percentile":"11.0"},"49":{"Rank":"901,175*","Names":"zfbend4960454 6","Link":"entry?entryID=19181800","R64":"210","R32":"220","R16":"80","R8":"0","R4":"0","R2":"0","Champ Pick":"Duke","Total":"510","Percentile":"11.0"}}