{"0":{"Rank":"194,401*","Names":"Dead President","Link":"entry?entryID=35387164","R64":"230","R32":"260","R16":"240","R8":"160","R4":"0","R2":"0","Champ Pick":"Duke","Total":"890","Percentile":"81.9"},"1":{"Rank":"194,401*","Names":"Chadwick ford 5","Link":"entry?entryID=35566164","R64":"230","R32":"260","R16":"240","R8":"160","R4":"0","R2":"0","Champ Pick":"Duke","Total":"890","Percentile":"81.9"},"2":{"Rank":"194,401*","Names":"Jager2569 9","Link":"entry?entryID=36154374","R64":"230","R32":"260","R16":"240","R8":"160","R4":"0","R2":"0","Champ Pick":"Duke","Total":"890","Percentile":"81.9"},"3":{"Rank":"194,401*","Names":"naps2213 4","Link":"entry?entryID=36549593","R64":"230","R32":"260","R16":"240","R8":"160","R4":"0","R2":"0","Champ Pick":"Duke","Total":"890","Percentile":"81.9"},"4":{"Rank":"194,401*","Names":"David27irishpride 3","Link":"entry?entryID=19953634","R64":"250","R32":"240","R16":"240","R8":"160","R4":"0","R2":"0","Champ Pick":"Tennessee","Total":"890","Percentile":"81.9"},"5":{"Rank":"194,401*","Names":"Bobby Bush","Link":"entry?entryID=20728798","R64":"250","R32":"240","R16":"240","R8":"160","R4":"0","R2":"0","Champ Pick":"Duke","Total":"890","Percentile":"81.9"},"6":{"Rank":"194,401*","Names":"WallKingwinnerrr","Link":"entry?entryID=20805717","R64":"250","R32":"240","R16":"240","R8":"160","R4":"0","R2":"0","Champ Pick":"Kentucky","Total":"890","Percentile":"81.9"},"7":{"Rank":"194,401*","Names":"masons","Link":"entry?entryID=21942889","R64":"250","R32":"240","R16":"240","R8":"160","R4":"0","R2":"0","Champ Pick":"Duke","Total":"890","Percentile":"81.9"},"8":{"Rank":"194,401*","Names":"oldschoolbucfan 1","Link":"entry?entryID=22812325","R64":"250","R32":"240","R16":"240","R8":"160","R4":"0","R2":"0","Champ Pick":"Auburn","Total":"890","Percentile":"81.9"},"9":{"Rank":"194,401*","Names":"tice9x6828217 1","Link":"entry?entryID=22875398","R64":"250","R32":"240","R16":"240","R8":"160","R4":"0","R2":"0","Champ Pick":"Duke","Total":"890","Percentile":"81.9"},"10":{"Rank":"194,401*","Names":"tommys7338627 1","Link":"entry?entryID=24643086","R64":"250","R32":"240","R16":"240","R8":"160","R4":"0","R2":"0","Champ Pick":"Gonzaga","Total":"890","Percentile":"81.9"},"11":{"Rank":"194,401*","Names":"ESPNFAN4500515343 9","Link":"entry?entryID=25257337","R64":"250","R32":"240","R16":"240","R8":"160","R4":"0","R2":"0","Champ Pick":"Purdue","Total":"890","Percentile":"81.9"},"12":{"Rank":"194,401*","Names":"CodyFaris 5","Link":"entry?entryID=25295466","R64":"250","R32":"240","R16":"240","R8":"160","R4":"0","R2":"0","Champ Pick":"Kentucky","Total":"890","Percentile":"81.9"},"13":{"Rank":"194,401*","Names":"ESPNFAN5971704519 9","Link":"entry?entryID=25302941","R64":"250","R32":"240","R16":"240","R8":"160","R4":"0","R2":"0","Champ Pick":"Purdue","Total":"890","Percentile":"81.9"},"14":{"Rank":"194,401*","Names":"f*ck duke","Link":"entry?entryID=25336519","R64":"250","R32":"240","R16":"240","R8":"160","R4":"0","R2":"0","Champ Pick":"Michigan State","Total":"890","Percentile":"81.9"},"15":{"Rank":"194,401*","Names":"ESPNFAN1435795145 5","Link":"entry?entryID=25399121","R64":"250","R32":"240","R16":"240","R8":"160","R4":"0","R2":"0","Champ Pick":"Gonzaga","Total":"890","Percentile":"81.9"},"16":{"Rank":"194,401*","Names":"ESPNFAN6481153706 19","Link":"entry?entryID=25504162","R64":"250","R32":"240","R16":"240","R8":"160","R4":"0","R2":"0","Champ Pick":"Kentucky","Total":"890","Percentile":"81.9"},"17":{"Rank":"194,401*","Names":"ESPNFAN04679471 4","Link":"entry?entryID=26006110","R64":"250","R32":"240","R16":"240","R8":"160","R4":"0","R2":"0","Champ Pick":"Auburn","Total":"890","Percentile":"81.9"},"18":{"Rank":"194,401*","Names":"espnfan3726268980 2","Link":"entry?entryID=26230106","R64":"250","R32":"240","R16":"240","R8":"160","R4":"0","R2":"0","Champ Pick":"Duke","Total":"890","Percentile":"81.9"},"19":{"Rank":"194,401*","Names":"rip UMBC","Link":"entry?entryID=26493578","R64":"250","R32":"240","R16":"240","R8":"160","R4":"0","R2":"0","Champ Pick":"North Carolina","Total":"890","Percentile":"81.9"},"20":{"Rank":"194,401*","Names":"espn09415676 7","Link":"entry?entryID=27453320","R64":"250","R32":"240","R16":"240","R8":"160","R4":"0","R2":"0","Champ Pick":"North Carolina","Total":"890","Percentile":"81.9"},"21":{"Rank":"194,401*","Names":"ESPNFAN4894724311 15","Link":"entry?entryID=27918332","R64":"250","R32":"240","R16":"240","R8":"160","R4":"0","R2":"0","Champ Pick":"Auburn","Total":"890","Percentile":"81.9"},"22":{"Rank":"194,401*","Names":"Benjamin Maas 15 6","Link":"entry?entryID=28113945","R64":"250","R32":"240","R16":"240","R8":"160","R4":"0","R2":"0","Champ Pick":"Gonzaga","Total":"890","Percentile":"81.9"},"23":{"Rank":"194,401*","Names":"Das Projekt 3","Link":"entry?entryID=28953619","R64":"250","R32":"240","R16":"240","R8":"160","R4":"0","R2":"0","Champ Pick":"North Carolina","Total":"890","Percentile":"81.9"},"24":{"Rank":"194,401*","Names":"ESPNFAN2862943081 21","Link":"entry?entryID=29026302","R64":"250","R32":"240","R16":"240","R8":"160","R4":"0","R2":"0","Champ Pick":"Duke","Total":"890","Percentile":"81.9"},"25":{"Rank":"194,401*","Names":"UNC","Link":"entry?entryID=29269751","R64":"250","R32":"240","R16":"240","R8":"160","R4":"0","R2":"0","Champ Pick":"North Carolina","Total":"890","Percentile":"81.9"},"26":{"Rank":"194,401*","Names":"ben 2","Link":"entry?entryID=29505720","R64":"250","R32":"240","R16":"240","R8":"160","R4":"0","R2":"0","Champ Pick":"North Carolina","Total":"890","Percentile":"81.9"},"27":{"Rank":"194,401*","Names":"Eric443371 1","Link":"entry?entryID=30201047","R64":"250","R32":"240","R16":"240","R8":"160","R4":"0","R2":"0","Champ Pick":"North Carolina","Total":"890","Percentile":"81.9"},"28":{"Rank":"194,401*","Names":"awilkinson802 22","Link":"entry?entryID=31087516","R64":"250","R32":"240","R16":"240","R8":"160","R4":"0","R2":"0","Champ Pick":"Michigan State","Total":"890","Percentile":"81.9"},"29":{"Rank":"194,401*","Names":"ESPNfan21357619 3","Link":"entry?entryID=31842235","R64":"250","R32":"240","R16":"240","R8":"160","R4":"0","R2":"0","Champ Pick":"Duke","Total":"890","Percentile":"81.9"},"30":{"Rank":"194,401*","Names":"Seter15 6","Link":"entry?entryID=32198148","R64":"250","R32":"240","R16":"240","R8":"160","R4":"0","R2":"0","Champ Pick":"Tennessee","Total":"890","Percentile":"81.9"},"31":{"Rank":"194,401*","Names":"espn95224646 7","Link":"entry?entryID=32452171","R64":"250","R32":"240","R16":"240","R8":"160","R4":"0","R2":"0","Champ Pick":"Michigan State","Total":"890","Percentile":"81.9"},"32":{"Rank":"194,401*","Names":"Alex9","Link":"entry?entryID=34051989","R64":"250","R32":"240","R16":"240","R8":"160","R4":"0","R2":"0","Champ Pick":"Tennessee","Total":"890","Percentile":"81.9"},"33":{"Rank":"194,401*","Names":"espn26535125 1","Link":"entry?entryID=34510206","R64":"250","R32":"240","R16":"240","R8":"160","R4":"0","R2":"0","Champ Pick":"Duke","Total":"890","Percentile":"81.9"},"34":{"Rank":"194,401*","Names":"Tyler Herro is my Hero","Link":"entry?entryID=23012826","R64":"270","R32":"220","R16":"240","R8":"160","R4":"0","R2":"0","Champ Pick":"Kentucky","Total":"890","Percentile":"81.9"},"35":{"Rank":"194,401*","Names":"espnfan9211310497 1","Link":"entry?entryID=24064153","R64":"270","R32":"220","R16":"240","R8":"160","R4":"0","R2":"0","Champ Pick":"Gonzaga","Total":"890","Percentile":"81.9"},"36":{"Rank":"194,401*","Names":"ESPNFAN3641607073 9","Link":"entry?entryID=25359962","R64":"270","R32":"220","R16":"240","R8":"160","R4":"0","R2":"0","Champ Pick":"Gonzaga","Total":"890","Percentile":"81.9"},"37":{"Rank":"194,401*","Names":"ESPNFAN3554655215 3","Link":"entry?entryID=28402380","R64":"270","R32":"220","R16":"240","R8":"160","R4":"0","R2":"0","Champ Pick":"Kentucky","Total":"890","Percentile":"81.9"},"38":{"Rank":"194,401*","Names":"ESPNFAN9363099499 19","Link":"entry?entryID=29004147","R64":"270","R32":"220","R16":"240","R8":"160","R4":"0","R2":"0","Champ Pick":"North Carolina","Total":"890","Percentile":"81.9"},"39":{"Rank":"194,401*","Names":"rhandch@ 2","Link":"entry?entryID=19165789","R64":"230","R32":"300","R16":"200","R8":"160","R4":"0","R2":"0","Champ Pick":"Kentucky","Total":"890","Percentile":"81.9"},"40":{"Rank":"194,401*","Names":"leahh24","Link":"entry?entryID=19925666","R64":"230","R32":"300","R16":"200","R8":"160","R4":"0","R2":"0","Champ Pick":"Michigan State","Total":"890","Percentile":"81.9"},"41":{"Rank":"194,401*","Names":"Anybody But Duke","Link":"entry?entryID=20051405","R64":"230","R32":"300","R16":"200","R8":"160","R4":"0","R2":"0","Champ Pick":"Gonzaga","Total":"890","Percentile":"81.9"},"42":{"Rank":"194,401*","Names":"17greenlatern 2","Link":"entry?entryID=23963069","R64":"230","R32":"300","R16":"200","R8":"160","R4":"0","R2":"0","Champ Pick":"Michigan State","Total":"890","Percentile":"81.9"},"43":{"Rank":"194,401*","Names":"Erich138 3","Link":"entry?entryID=25122212","R64":"230","R32":"300","R16":"200","R8":"160","R4":"0","R2":"0","Champ Pick":"North Carolina","Total":"890","Percentile":"81.9"},"44":{"Rank":"194,401*","Names":"Goody2517","Link":"entry?entryID=25304426","R64":"230","R32":"300","R16":"200","R8":"160","R4":"0","R2":"0","Champ Pick":"North Carolina","Total":"890","Percentile":"81.9"},"45":{"Rank":"194,401*","Names":"No Ones busting my bracket ","Link":"entry?entryID=30082341","R64":"230","R32":"300","R16":"200","R8":"160","R4":"0","R2":"0","Champ Pick":"North Carolina","Total":"890","Percentile":"81.9"},"46":{"Rank":"194,401*","Names":"Ericsluder1 11","Link":"entry?entryID=30267434","R64":"230","R32":"300","R16":"200","R8":"160","R4":"0","R2":"0","Champ Pick":"North Carolina","Total":"890","Percentile":"81.9"},"47":{"Rank":"194,401*","Names":"ESPNFAN1323686639 13","Link":"entry?entryID=30423179","R64":"230","R32":"300","R16":"200","R8":"160","R4":"0","R2":"0","Champ Pick":"Michigan State","Total":"890","Percentile":"81.9"},"48":{"Rank":"194,401*","Names":"espn50183272 19","Link":"entry?entryID=32123661","R64":"230","R32":"300","R16":"200","R8":"160","R4":"0","R2":"0","Champ Pick":"Michigan State","Total":"890","Percentile":"81.9"},"49":{"Rank":"194,401*","Names":"JoeManolescu28 10","Link":"entry?entryID=33721069","R64":"230","R32":"300","R16":"200","R8":"160","R4":"0","R2":"0","Champ Pick":"Duke","Total":"890","Percentile":"81.9"}}